{"l3vpn-1": {"requestData": {"l3vpn-svc": {"vpn-svc": {"topology": "any-to-any"}, "sites": {"site": [{"site-network-accesses": {"site-network-access": {"ip-connection": {"ipv4": {"provider-address": "10.1.1.1", "mask": 24}}, "provider-edge": {"router-name": "P2", "interface-name": "GigabitEthernet0/0/0/4"}, "routing-protocols": {"routing-protocol": {"type": "ospf", "ospf": {"area-address": "0", "address-family": "ipv4-unicast"}}}}}}, {"site-network-accesses": {"site-network-access": {"ip-connection": {"ipv4": {"provider-address": "40.5.5.1", "mask": 24, "customer-address": "40.5.5.5"}}, "provider-edge": {"router-name": "PE3", "interface-name": "ge-0/0/1"}, "routing-protocols": {"routing-protocol": {"bgp": {"site-of-origin": "1.1.1.1:1", "address-family": "ipv4-unicast", "autonomous-system": 65002}, "type": "bgp"}}}}}, {"site-network-accesses": {"site-network-access": {"ip-connection": {"ipv4": {"provider-address": "10.5.5.5", "mask": 24, "customer-address": "40.5.5.5"}}, "provider-edge": {"router-name": "P5", "interface-name": "GigabitEthernet2"}, "routing-protocols": {"routing-protocol": {"bgp": {"site-of-origin": "1.1.1.1:1", "address-family": "ipv4-unicast", "autonomous-system": 65002}, "type": "bgp"}}}}}]}}}, "serviceType": "l3vpn", "name": "l3vpn-1", "createdOn": "2016-11-08 23:12:15", "serviceState": "Reserved", "href": "/services/652dfba6-81f6-4e7a-9ee9-26f99b4500dc", "createdBy": "dsm", "service-attributes": {"route_target": "65000:15", "ospf_id": "1243", "policy_name": "bgp-into-ospf", "route_distinguisher": "65000:15", "local_as_number": "65001", "vrf_name": "l3vpn-1", "domain_id": "1605"}, "id": "652dfba6-81f6-4e7a-9ee9-26f99b4500dc"}}